{
    "applicationList": [
        {
            "appName": "WhatsTouch",
            "appReview": "4.9/5",
            "appIcon": "",
            "adBackground": "https://raw.githubusercontent.com/bannarisoftwares/whatstouch-api/master/v1/ApplicationAds/icons/app-promote_1.png",
            "appDescription": "",
            "buttonName": "View",
            "isFullScreenAd": false,
            "appLink": "https://play.google.com/store/apps/details?id=com.softwares.bannari.whatstouch","appId":"EX_0002"
        }
    ]
}